climates/__init__.py
climates/conftest.py
climates/parameters.py
climates/py.typed
climates/test_climates.py
climates-0.0.4.dist-info/LICENSE
climates-0.0.4.dist-info/METADATA
climates-0.0.4.dist-info/WHEEL
climates-0.0.4.dist-info/top_level.txt
climates-0.0.4.dist-info/RECORD
