Metadata-Version: 2.1
Name: climates
Version: 0.0.4
Summary: Command-line interfaces made accessible to even simpletons
Home-page: https://github.com/lggruspe/climates
Author: Levi Gruspe
Author-email: mail.levig@gmail.com
License: UNKNOWN
Platform: UNKNOWN
Classifier: Programming Language :: Python :: 3
Classifier: Programming Language :: Python :: 3.8
Classifier: Programming Language :: Python :: 3.9
Classifier: License :: OSI Approved :: MIT License
Classifier: Environment :: Console
Requires-Python: >=3.8
